collective/__init__.py
collective/deletepermission/.gitignore
collective/deletepermission/__init__.py
collective/deletepermission/configure.zcml
collective/deletepermission/copy.py
collective/deletepermission/cut_paste_object.py
collective/deletepermission/del_object_dexterity.py
collective/deletepermission/permissions.zcml
collective/deletepermission/rename.py
collective/deletepermission/testing.py
collective/deletepermission/profiles/default/actions.xml
collective/deletepermission/profiles/default/metadata.xml
collective/deletepermission/profiles/default/rolemap.xml
collective/deletepermission/profiles/uninstall/actions.xml
collective/deletepermission/profiles/uninstall/metadata.xml
collective/deletepermission/profiles/uninstall/rolemap.xml
collective/deletepermission/tests/__init__.py
collective/deletepermission/tests/base.py
collective/deletepermission/tests/test_actions.py
collective/deletepermission/tests/test_browser_statusmessages.py
collective/deletepermission/tests/test_copy.py
collective/deletepermission/tests/test_correct_permission.py
collective/deletepermission/tests/test_creation.py
collective/deletepermission/tests/test_cut_permission.py
collective/deletepermission/tests/test_delete.py
collective/deletepermission/tests/test_permission_functional.py
collective/deletepermission/tests/test_remove_only_files.py
collective/deletepermission/upgrades/__init__.py
collective/deletepermission/upgrades/configure.zcml
collective_deletepermission-2.0.0a3.dist-info/METADATA
collective_deletepermission-2.0.0a3.dist-info/WHEEL
collective_deletepermission-2.0.0a3.dist-info/entry_points.txt
collective_deletepermission-2.0.0a3.dist-info/top_level.txt
collective_deletepermission-2.0.0a3.dist-info/RECORD
