Metadata-Version: 2.4
Name: collective.deletepermission
Version: 2.0.0a3
Summary: Implements a new permission 'Delete portal content'
Author-email: "Mathias Leimgruber (webcloud7 ag)" <m.leimgruber@webcloud7.ch>
License-Expression: GPL-2.0-only
Project-URL: Homepage, https://github.com/collective/collective.deletepermission
Project-URL: Repository, https://github.com/collective/collective.deletepermission
Project-URL: Issues, https://github.com/collective/collective.deletepermission/issues
Keywords: collective,deletepermission,webcloud7,plone
Classifier: Development Status :: 5 - Production/Stable
Classifier: Framework :: Plone
Classifier: Framework :: Plone :: 6.1
Classifier: Intended Audience :: Developers
Classifier: Programming Language :: Python
Classifier: Programming Language :: Python :: 3
Classifier: Programming Language :: Python :: 3.11
Classifier: Programming Language :: Python :: 3.12
Classifier: Programming Language :: Python :: 3.13
Classifier: Topic :: Software Development :: Libraries :: Python Modules
Requires-Python: >=3.11
Requires-Dist: AccessControl
Requires-Dist: Acquisition
Requires-Dist: Products.CMFCore
Requires-Dist: Products.CMFPlone
Requires-Dist: Products.GenericSetup
Requires-Dist: Products.PythonScripts
Requires-Dist: ZODB
Requires-Dist: Zope
Requires-Dist: collective.monkeypatcher
Requires-Dist: setuptools
Requires-Dist: zope.container
Requires-Dist: zope.event
Requires-Dist: zope.lifecycleevent
Provides-Extra: test
Requires-Dist: AccessControl; extra == "test"
Requires-Dist: Products.CMFCore; extra == "test"
Requires-Dist: Products.GenericSetup; extra == "test"
Requires-Dist: Products.statusmessages; extra == "test"
Requires-Dist: Zope; extra == "test"
Requires-Dist: beautifulsoup4; extra == "test"
Requires-Dist: plone.api>=1.3.0; extra == "test"
Requires-Dist: plone.app.contenttypes; extra == "test"
Requires-Dist: plone.app.dexterity; extra == "test"
Requires-Dist: plone.app.portlets; extra == "test"
Requires-Dist: plone.app.testing; extra == "test"
Requires-Dist: plone.autoform; extra == "test"
Requires-Dist: requests; extra == "test"
Requires-Dist: transaction; extra == "test"
Requires-Dist: zExceptions; extra == "test"
Requires-Dist: zope.interface; extra == "test"
